twisted/plugins/xslproxy_service.py
xslproxy/_init_.py
xslproxy/server.py
xslproxy/service.py
xslproxy/web.py
xslproxy/xsl.py
xslproxy-1.2.0.dist-info/COPYING
xslproxy-1.2.0.dist-info/METADATA
xslproxy-1.2.0.dist-info/WHEEL
xslproxy-1.2.0.dist-info/top_level.txt
xslproxy-1.2.0.dist-info/RECORD
