Metadata-Version: 2.1
Name: xslproxy
Version: 1.2.0
Summary: Xsl transforming reverse proxy based on twisted
Home-page: https://github.com/znerol/xslproxy
Author: Lorenz Schori
Author-email: lo@znerol.ch
License: UNKNOWN
Platform: UNKNOWN
Classifier: Development Status :: 5 - Production/Stable
Classifier: Environment :: Plugins
Classifier: Framework :: Twisted
Classifier: Intended Audience :: Developers
Classifier: Intended Audience :: Information Technology
Classifier: License :: OSI Approved :: GNU Affero General Public License v3 or later (AGPLv3+)
Classifier: Operating System :: OS Independent
Classifier: Programming Language :: Python :: 3.5
Classifier: Programming Language :: Python :: 3.6
Classifier: Programming Language :: Python :: 3.7
Classifier: Programming Language :: Python :: 3.8
Classifier: Topic :: Internet :: Proxy Servers
Requires-Python: >=3.5
License-File: COPYING
Requires-Dist: Twisted[tls]
Requires-Dist: defusedxml
Requires-Dist: zope.interface
Requires-Dist: lxml
